DriveUtility/__init__.py
DriveUtility/__main__.py
DriveUtility/addContext.py
DriveUtility/banner.py
DriveUtility/clean_bin.py
DriveUtility/client_secret.json
DriveUtility/drive.py
DriveUtility/main.py
DriveUtility/removeContext.py
DriveUtility/bin/DriveUtil.py
DriveUtility/bin/__init__.py
DriveUtility/cmd/createFolder.bat
DriveUtility/cmd/delete.bat
DriveUtility/cmd/download.bat
DriveUtility/cmd/list.bat
DriveUtility/cmd/move.bat
DriveUtility/cmd/removeOauth.bat
DriveUtility/cmd/upload (specific).bat
DriveUtility/cmd/upload.bat
DriveUtility-1.1.18.dist-info/LICENSE.txt
DriveUtility-1.1.18.dist-info/METADATA
DriveUtility-1.1.18.dist-info/RECORD
DriveUtility-1.1.18.dist-info/WHEEL
DriveUtility-1.1.18.dist-info/entry_points.txt
DriveUtility-1.1.18.dist-info/top_level.txt
