Metadata-Version: 2.1
Name: DriveUtility
Version: 1.1.18
Summary: Google Drive tool
Home-page: https://github.com/PeterGabaldon/DriveUtility
Author: Pedro Gabaldon Julia
Author-email: petergj@protonmail.com
License: MIT
Platform: UNKNOWN
Classifier: Programming Language :: Python :: 2.7
Classifier: License :: OSI Approved :: MIT License
Classifier: Development Status :: 4 - Beta
Requires-Dist: oauth2client
Requires-Dist: httplib2
Requires-Dist: google-api-python-client
